klarna/__init__.py
klarna/authorizations.py
klarna/orders.py
klarna/sdk.py
klarna/sessions.py
klarna/tokens.py
klarna/models/__init__.py
klarna/models/operations/__init__.py
klarna/models/operations/cancelauthorization.py
klarna/models/operations/createcreditsession.py
klarna/models/operations/createorder.py
klarna/models/operations/purchasetoken.py
klarna/models/operations/readcreditsession.py
klarna/models/operations/updatecreditsession.py
klarna/models/shared/__init__.py
klarna/models/shared/address.py
klarna/models/shared/asset_urls.py
klarna/models/shared/attachment.py
klarna/models/shared/authorized_payment_method.py
klarna/models/shared/create_order_request.py
klarna/models/shared/customer.py
klarna/models/shared/customer_read.py
klarna/models/shared/customer_read_create_token.py
klarna/models/shared/customer_token_creation_request.py
klarna/models/shared/customer_token_creation_response.py
klarna/models/shared/errorv2.py
klarna/models/shared/merchant_session.py
klarna/models/shared/merchant_urls.py
klarna/models/shared/options.py
klarna/models/shared/order.py
klarna/models/shared/order_line.py
klarna/models/shared/payment_method_category.py
klarna/models/shared/product_identifiers.py
klarna/models/shared/security.py
klarna/models/shared/session.py
klarna/models/shared/session_create.py
klarna/models/shared/session_read.py
klarna/models/shared/subscription.py
klarna/utils/__init__.py
klarna/utils/retries.py
klarna/utils/utils.py
klarna_orders-1.1.1.dist-info/LICENSE.md
klarna_orders-1.1.1.dist-info/METADATA
klarna_orders-1.1.1.dist-info/WHEEL
klarna_orders-1.1.1.dist-info/top_level.txt
klarna_orders-1.1.1.dist-info/RECORD
